music_album_creation/__init__.py
music_album_creation/album_segmentation.py
music_album_creation/create_album.py
music_album_creation/dialogs.py
music_album_creation/display-logo.sh
music_album_creation/downloading.py
music_album_creation/metadata.py
music_album_creation/tracks_parsing.py
music_album_creation/format_classification/__init__.py
music_album_creation/format_classification/dataset.py
music_album_creation/format_classification/tracks_format_classifier.py
music_album_creation/format_classification/data/dev-split.txt
music_album_creation/format_classification/data/model.pickle
music_album_creation/format_classification/data/model1
music_album_creation/format_classification/data/test-split.txt
music_album_creation/format_classification/data/train-split.txt
music_album_creator-0.5.3.dist-info/DESCRIPTION.rst
music_album_creator-0.5.3.dist-info/METADATA
music_album_creator-0.5.3.dist-info/RECORD
music_album_creator-0.5.3.dist-info/WHEEL
music_album_creator-0.5.3.dist-info/entry_points.txt
music_album_creator-0.5.3.dist-info/metadata.json
music_album_creator-0.5.3.dist-info/top_level.txt
testing/__init__.py
testing/test_classifier.py
testing/test_downloading.py
testing/test_segmenting.py
