Metadata-Version: 2.0
Name: music-album-creator
Version: 0.5.3
Summary: A CLI application intending to automate offline music library building
Home-page: UNKNOWN
Author: UNKNOWN
Author-email: UNKNOWN
License: GNU GPLv3
Keywords: music album automation youtube audio metadata download
Platform: UNKNOWN
Classifier: Development Status :: 4 - Beta
Classifier: License :: OSI Approved :: GNU General Public License v3 (GPLv3)
Classifier: Programming Language :: Python :: 3.5
Classifier: Topic :: Software Development :: Libraries :: Python Modules
Classifier: Topic :: Multimedia :: Sound/Audio :: Conversion
Classifier: Topic :: Multimedia :: Sound/Audio :: Editors
Classifier: Intended Audience :: Science/Research
Requires-Dist: tqdm
Requires-Dist: click
Requires-Dist: sklearn
Requires-Dist: mutagen
Requires-Dist: PyInquirer
Requires-Dist: youtube-dl
